recs/__init__.py
recs/__main__.py
recs/audio/__init__.py
recs/audio/block.py
recs/audio/channel_writer.py
recs/audio/file_opener.py
recs/audio/header_size.py
recs/base/__init__.py
recs/base/_query_device.py
recs/base/cfg_raw.py
recs/base/prefix_dict.py
recs/base/pyproject.py
recs/base/state.py
recs/base/times.py
recs/base/type_conversions.py
recs/base/types.py
recs/cfg/__init__.py
recs/cfg/aliases.py
recs/cfg/app.py
recs/cfg/cfg.py
recs/cfg/cli.py
recs/cfg/device.py
recs/cfg/hash_cmp.py
recs/cfg/metadata.py
recs/cfg/path_pattern.py
recs/cfg/run_cli.py
recs/cfg/time_settings.py
recs/cfg/track.py
recs/misc/__init__.py
recs/misc/contexts.py
recs/misc/counter.py
recs/misc/file_list.py
recs/misc/legal_filename.py
recs/misc/log.py
recs/ui/__init__.py
recs/ui/device_process.py
recs/ui/device_recorder.py
recs/ui/device_tracks.py
recs/ui/full_state.py
recs/ui/live.py
recs/ui/recorder.py
recs/ui/table.py
recs-0.3.1.dist-info/LICENSE
recs-0.3.1.dist-info/METADATA
recs-0.3.1.dist-info/WHEEL
recs-0.3.1.dist-info/entry_points.txt
recs-0.3.1.dist-info/RECORD
