Metadata-Version: 2.1
Name: recs
Version: 0.3.1
Summary: 🎙 recs: the Universal Recorder 🎙
License: MIT
Author: Tom Ritchford
Author-email: tom@swirly.com
Requires-Python: >=3.10
Classifier: License :: OSI Approved :: MIT License
Classifier: Programming Language :: Python :: 3
Classifier: Programming Language :: Python :: 3.10
Classifier: Programming Language :: Python :: 3.11
Classifier: Programming Language :: Python :: 3.12
Requires-Dist: coverage
Requires-Dist: dtyper
Requires-Dist: humanfriendly
Requires-Dist: impall
Requires-Dist: numpy
Requires-Dist: overrides
Requires-Dist: pyaudio
Requires-Dist: rich
Requires-Dist: sounddevice
Requires-Dist: soundfile
Requires-Dist: strenum
Requires-Dist: threa (>=1.9.0)
Requires-Dist: tomli
Requires-Dist: typer
